setup.py
vend/__init__.py
vendpos.egg-info/PKG-INFO
vendpos.egg-info/SOURCES.txt
vendpos.egg-info/dependency_links.txt
vendpos.egg-info/not-zip-safe
vendpos.egg-info/requires.txt
vendpos.egg-info/top_level.txt