Metadata-Version: 1.0
Name: vendpos
Version: 0.1
Summary: vend pos python
Home-page: https://github.com/royendgel/vend-python
Author: Royendgel Silberie
Author-email: rsilberie@techprocur.com
License: MIT
Platform: UNKNOWN
